[
  {
    "transaction_type": "cash_power",
    "txid": "14103506143",
    "amount": 4000.0,
    "currency": "RWF",
    "token": "72962-79980-44699-06073",
    "timestamp": "2024-05-26 13:31:00",
    "new_balance": 800.0,
    "raw_message": "*162*txid:14103506143*s*your payment of 4000 rwf to mtn cash power with token 72962-79980-44699-06073 has been completed at 2024-05-26 13:31:00. fee was 0 rwf. your new balance: 800 rwf . message: - -. *en#",
    "line_number": 1
  },
  {
    "transaction_type": "cash_power",
    "txid": "14264876273",
    "amount": 2000.0,
    "currency": "RWF",
    "token": "06476-53398-98517-06704",
    "timestamp": "2024-06-06 18:34:13",
    "new_balance": 830.0,
    "raw_message": "*162*txid:14264876273*s*your payment of 2000 rwf to mtn cash power with token 06476-53398-98517-06704 has been completed at 2024-06-06 18:34:13. fee was 0 rwf. your new balance: 830 rwf . message: - -. *en#",
    "line_number": 2
  },
  {
    "transaction_type": "cash_power",
    "txid": "14405681742",
    "amount": 1000.0,
    "currency": "RWF",
    "token": "40296-92192-79801-46115",
    "timestamp": "2024-06-16 21:05:53",
    "new_balance": 1350.0,
    "raw_message": "*162*txid:14405681742*s*your payment of 1000 rwf to mtn cash power with token 40296-92192-79801-46115 has been completed at 2024-06-16 21:05:53. fee was 0 rwf. your new balance: 1350 rwf . message: - -. *en#",
    "line_number": 3
  },
  {
    "transaction_type": "cash_power",
    "txid": "14469963984",
    "amount": 2000.0,
    "currency": "RWF",
    "token": "09779-88882-62297-78749",
    "timestamp": "2024-06-21 16:48:15",
    "new_balance": 640.0,
    "raw_message": "*162*txid:14469963984*s*your payment of 2000 rwf to mtn cash power with token 09779-88882-62297-78749 has been completed at 2024-06-21 16:48:15. fee was 0 rwf. your new balance: 640 rwf . message: - -. *en#",
    "line_number": 4
  },
  {
    "transaction_type": "cash_power",
    "txid": "14540224719",
    "amount": 1000.0,
    "currency": "RWF",
    "token": "70836-02982-06384-28148",
    "timestamp": "2024-06-26 18:43:34",
    "new_balance": 3910.0,
    "raw_message": "*162*txid:14540224719*s*your payment of 1000 rwf to mtn cash power with token 70836-02982-06384-28148 has been completed at 2024-06-26 18:43:34. fee was 0 rwf. your new balance: 3910 rwf . message: - -. *en#",
    "line_number": 5
  },
  {
    "transaction_type": "cash_power",
    "txid": "15507397966",
    "amount": 5000.0,
    "currency": "RWF",
    "token": "40189-29433-02084-41228",
    "timestamp": "2024-08-31 11:31:17",
    "new_balance": 30670.0,
    "raw_message": "*162*txid:15507397966*s*your payment of 5000 rwf to mtn cash power with token 40189-29433-02084-41228 has been completed at 2024-08-31 11:31:17. fee was 0 rwf. your new balance: 30670 rwf . message: - -. *en#",
    "line_number": 6
  },
  {
    "transaction_type": "cash_power",
    "txid": "15611958408",
    "amount": 20000.0,
    "currency": "RWF",
    "token": "45758-92310-31845-02327",
    "timestamp": "2024-09-06 21:07:37",
    "new_balance": 192990.0,
    "raw_message": "*162*txid:15611958408*s*your payment of 20000 rwf to mtn cash power with token 45758-92310-31845-02327 has been completed at 2024-09-06 21:07:37. fee was 0 rwf. your new balance: 192990 rwf . message: - -. *en#",
    "line_number": 7
  },
  {
    "transaction_type": "cash_power",
    "txid": "16016087305",
    "amount": 10000.0,
    "currency": "RWF",
    "token": "65361-75345-33963-16846",
    "timestamp": "2024-10-02 20:41:16",
    "new_balance": 69612.0,
    "raw_message": "*162*txid:16016087305*s*your payment of 10000 rwf to mtn cash power with token 65361-75345-33963-16846 has been completed at 2024-10-02 20:41:16. fee was 0 rwf. your new balance: 69612 rwf . message: - -. *en#",
    "line_number": 8
  },
  {
    "transaction_type": "cash_power",
    "txid": "17140081149",
    "amount": 2000.0,
    "currency": "RWF",
    "token": "50919-80431-28076-85133",
    "timestamp": "2024-11-30 00:11:51",
    "new_balance": 17012.0,
    "raw_message": "*162*txid:17140081149*s*your payment of 2000 rwf to mtn cash power with token 50919-80431-28076-85133 has been completed at 2024-11-30 00:11:51. fee was 0 rwf. your new balance: 17012 rwf . message: - -. *en#",
    "line_number": 9
  },
  {
    "transaction_type": "cash_power",
    "txid": "17344287393",
    "amount": 4000.0,
    "currency": "RWF",
    "token": "13020-24529-63630-27675",
    "timestamp": "2024-12-10 00:40:41",
    "new_balance": 742.0,
    "raw_message": "*162*txid:17344287393*s*your payment of 4000 rwf to mtn cash power with token 13020-24529-63630-27675 has been completed at 2024-12-10 00:40:41. fee was 0 rwf. your new balance: 742 rwf . message: - -. *en#",
    "line_number": 10
  },
  {
    "transaction_type": "cash_power",
    "txid": "17708814651",
    "amount": 10000.0,
    "currency": "RWF",
    "token": "55566-87602-29972-88164",
    "timestamp": "2024-12-27 11:59:34",
    "new_balance": 48134.0,
    "raw_message": "*162*txid:17708814651*s*your payment of 10000 rwf to mtn cash power with token 55566-87602-29972-88164 has been completed at 2024-12-27 11:59:34. fee was 0 rwf. your new balance: 48134 rwf . message: - electricity units: 37.2kwh.. *en#",
    "line_number": 11
  }
]